rotspectools/.DS_Store
rotspectools/__init__.py
rotspectools/cat.py
rotspectools/cli.py
rotspectools/rotspectools.py
rotspectools-0.1.11.dist-info/LICENSE
rotspectools-0.1.11.dist-info/METADATA
rotspectools-0.1.11.dist-info/WHEEL
rotspectools-0.1.11.dist-info/RECORD
