Metadata-Version: 2.1
Name: rotspectools
Version: 0.1.11
Summary: 
License: MIT
Author: Dairen Jean
Requires-Python: >=3.8,<4.0
Classifier: License :: OSI Approved :: MIT License
Classifier: Programming Language :: Python :: 3
Classifier: Programming Language :: Python :: 3.8
Classifier: Programming Language :: Python :: 3.9
Classifier: Programming Language :: Python :: 3.10
Classifier: Programming Language :: Python :: 3.11
Requires-Dist: SciencePlots (>=2.1.0,<3.0.0)
Requires-Dist: matplotlib (>=3.7.1,<4.0.0)
Requires-Dist: numpy (>=1.24.3,<2.0.0)
Requires-Dist: openpyxl (>=3.1.2,<4.0.0)
Requires-Dist: pandas (>=2.0.2,<3.0.0)
Requires-Dist: pathlib (>=1.0.1,<2.0.0)
